nslsii/__init__.py
nslsii/_version.py
nslsii/ad33.py
nslsii/devices.py
nslsii/epics_utils.py
nslsii/kafka_utils.py
nslsii/md_dict.py
nslsii/re_subs.py
nslsii/temperature_controllers.py
nslsii/transforms.py
nslsii/utils.py
nslsii/areadetector/__init__.py
nslsii/areadetector/xspress3.py
nslsii/common/__init__.py
nslsii/common/touchbl.py
nslsii/common/ipynb/__init__.py
nslsii/common/ipynb/animation.py
nslsii/common/ipynb/info.py
nslsii/common/ipynb/logutils.py
nslsii/common/ipynb/nbviewer.py
nslsii/detectors/QEPro.py
nslsii/detectors/__init__.py
nslsii/detectors/maia.py
nslsii/detectors/trigger_mixins.py
nslsii/detectors/utils.py
nslsii/detectors/webcam.py
nslsii/detectors/xspress3.py
nslsii/detectors/zebra.py
nslsii/iocs/__init__.py
nslsii/iocs/caproto_saver.py
nslsii/iocs/eps_two_state_ioc_sim.py
nslsii/iocs/thermo_sim.py
nslsii/iocs/utils.py
nslsii/motors/__init__.py
nslsii/motors/delta_tau.py
nslsii/ophyd_async/__init__.py
nslsii/ophyd_async/providers.py
nslsii/ophyd_async/devices/__init__.py
nslsii/ophyd_async/devices/rbd9103.py
nslsii/plans/__init__.py
nslsii/plans/maia.py
nslsii/sync_experiment/__init__.py
nslsii/sync_experiment/__main__.py
nslsii/sync_experiment/sync_experiment.py
nslsii-0.11.7.dist-info/licenses/LICENSE
nslsii-0.11.7.dist-info/METADATA
nslsii-0.11.7.dist-info/WHEEL
nslsii-0.11.7.dist-info/entry_points.txt
nslsii-0.11.7.dist-info/top_level.txt
nslsii-0.11.7.dist-info/RECORD
