Metadata-Version: 2.4
Name: nslsii
Version: 0.11.7
Summary: Tools for data collection and analysis at NSLS-II
Author: Brookhaven National Laboratory
License: BSD (3-clause)
License-File: LICENSE
Requires-Dist: appdirs
Requires-Dist: bluesky-kafka>=0.8.0
Requires-Dist: bluesky>=1.8.1
Requires-Dist: caproto
Requires-Dist: databroker
Requires-Dist: h5py
Requires-Dist: httpx
Requires-Dist: ipython
Requires-Dist: ipywidgets
Requires-Dist: ldap3
Requires-Dist: matplotlib
Requires-Dist: msgpack>=1.0.0
Requires-Dist: msgpack-numpy
Requires-Dist: numpy
Requires-Dist: opencv-python
Requires-Dist: ophyd
Requires-Dist: ophyd-async
Requires-Dist: packaging
Requires-Dist: pillow
Requires-Dist: psutil
Requires-Dist: pycryptodome
Requires-Dist: pyolog
Requires-Dist: redis
Requires-Dist: redis-json-dict
Requires-Dist: requests
Requires-Dist: setuptools
Requires-Dist: shortuuid
Dynamic: author
Dynamic: description
Dynamic: description-content-type
Dynamic: license
Dynamic: license-file
Dynamic: requires-dist
Dynamic: summary
